{
  "commit": "4e7e0f5fc9ca61ea2f3014ae1cfa88309efe100e",
  "summary": "chore(deps): bump http-proxy-middleware from 2.0.9 to 4.1.1",
  "description": "Bumps [http-proxy-middleware](https://github.com/chimurai/http-proxy-middleware) from 2.0.9 to 4.1.1.\n- [Release notes](https://github.com/chimurai/http-proxy-middleware/releases)\n- [Changelog](https://github.com/chimurai/http-proxy-middleware/blob/master/CHANGELOG.md)\n- [Commits](https://github.com/chimurai/http-proxy-middleware/compare/v2.0.9...v4.1.1)\n\n---\nupdated-dependencies:\n- dependency-name: http-proxy-middleware\n  dependency-version: 4.1.1\n  dependency-type: direct:production\n...\n\nSigned-off-by: dependabot[bot] <support@github.com>",
  "timestamp": 1781940883000,
  "storybooks": [
    "email-renderer",
    "fxa-react",
    "fxa-settings"
  ],
  "deployDir": "deploy/"
}